README
setup.py
scripts/tenper-completion.sh
tenper/__init__.py
tenper/command.py
tenper/config.py
tenper/config_template.yml
tenper/core.py
tenper/core_test.py
tenper.egg-info/PKG-INFO
tenper.egg-info/SOURCES.txt
tenper.egg-info/dependency_links.txt
tenper.egg-info/entry_points.txt
tenper.egg-info/requires.txt
tenper.egg-info/top_level.txt