Metadata-Version: 1.1
Name: tenper
Version: 1.2.2
Summary: A tmux session manager with optional virtualenv support.
Home-page: https://github.com/mqsoh/tenper
Author: Mason Staugler
Author-email: mason@staugler.net
License: MIT license
Keywords: tmux,virtualenv,virtualenvwrapper
Platform: UNKNOWN
Classifier: Programming Language :: Python :: 3
Classifier: Development Status :: 4 - Beta
Classifier: Environment :: Console
Classifier: Intended Audience :: Developers
Classifier: License :: OSI Approved :: MIT License
